hive_cli/__init__.py
hive_cli/config.py
hive_cli/main.py
hive_cli/libs/Dockerfile
hive_cli/libs/__init__.py
hive_cli/libs/common_tools.py
hive_cli/libs/main.py
hive_cli/libs/pyproject.toml
hive_cli/platform/__init__.py
hive_cli/platform/base.py
hive_cli/platform/k8s.py
hive_cli/platform/onprem.py
hive_cli/runtime/__init__.py
hive_cli/runtime/runtime.py
hive_cli/utils/__init__.py
hive_cli/utils/event.py
hive_cli/utils/git.py
hive_cli/utils/image.py
hive_cli/utils/logger.py
hive_cli/utils/time.py
hiverge_cli-0.3.2.dist-info/licenses/LICENSE
hiverge_cli-0.3.2.dist-info/METADATA
hiverge_cli-0.3.2.dist-info/WHEEL
hiverge_cli-0.3.2.dist-info/entry_points.txt
hiverge_cli-0.3.2.dist-info/top_level.txt
hiverge_cli-0.3.2.dist-info/RECORD
