Metadata-Version: 2.4
Name: hiverge-cli
Version: 0.3.2
Summary: Universal Command Line Interface for Hive agent.
Author: Hiverge Team
Classifier: Programming Language :: Python :: 3
Classifier: License :: OSI Approved :: MIT License
Classifier: Operating System :: OS Independent
Requires-Python: >=3.12
License-File: LICENSE
Requires-Dist: PyYAML>=5.1
Requires-Dist: pydantic>=1.8.2
Requires-Dist: gitpython>=3.1.24
Requires-Dist: rich>=12.5.1
Requires-Dist: kubernetes>=33.1.0
Requires-Dist: portforward>=0.3.0
Dynamic: license-file
